subpixel_edges/__init__.py
subpixel_edges/circle.py
subpixel_edges/edgepixel.py
subpixel_edges/edges_iter0.py
subpixel_edges/edges_iter1.py
subpixel_edges/edges_iterN.py
subpixel_edges/final_detector_iter0.py
subpixel_edges/final_detector_iter1.py
subpixel_edges/final_detector_iterN.py
subpixel_edges-0.1.1.dist-info/AUTHORS.md
subpixel_edges-0.1.1.dist-info/LICENSE
subpixel_edges-0.1.1.dist-info/METADATA
subpixel_edges-0.1.1.dist-info/WHEEL
subpixel_edges-0.1.1.dist-info/top_level.txt
subpixel_edges-0.1.1.dist-info/RECORD
