Metadata-Version: 2.1
Name: subpixel-edges
Version: 0.1.1
Summary: Pure Python implementation of subpixel edge location algorithm based on partial area effect
Home-page: https://github.com/gravi-toni/subpixel-edges
Author: GraviToni
License: MIT
Platform: UNKNOWN
Classifier: Intended Audience :: Developers
Classifier: Intended Audience :: Education
Classifier: Intended Audience :: Science/Research
Classifier: License :: OSI Approved :: MIT License
Classifier: Programming Language :: Python :: 3
Classifier: Topic :: Software Development :: Libraries
Classifier: Topic :: Software Development :: Libraries :: Python Modules
Requires-Python: >=3.0
Requires-Dist: numpy (>=1.18.4)
Requires-Dist: scipy (>=1.4.1)
Requires-Dist: numba (>=0.49)
Provides-Extra: examples
Requires-Dist: matplotlib (>=3.2.1) ; extra == 'examples'
Requires-Dist: opencv-python (>=4.1.0.25) ; extra == 'examples'
Provides-Extra: tests
Requires-Dist: pytest ; extra == 'tests'
Requires-Dist: opencv-python (>=4.1.0.25) ; extra == 'tests'
